{
  "type" : "FeatureCollection",
  "features" : [{"type":"Feature","id":12,"geometry":{"type":"Point","coordinates":[30.539709479000066,25.443380157000036]},"properties":{"OBJECTID":12,"Name":"مطبق","code":"502","description":"عمق 2.5 م"}},{"type":"Feature","id":13,"geometry":{"type":"Point","coordinates":[30.53977503200008,25.443386037000039]},"properties":{"OBJECTID":13,"Name":"مطبق","code":"502","description":"عمق 2.5 م"}},{"type":"Feature","id":16,"geometry":{"type":"Point","coordinates":[30.539941960000078,25.443371576000061]},"properties":{"OBJECTID":16,"Name":"مطبق","code":"502","description":"عمق 2.5 م"}},{"type":"Feature","id":17,"geometry":{"type":"Point","coordinates":[30.540402622000045,25.443329196000036]},"properties":{"OBJECTID":17,"Name":"مطبق","code":"502","description":"عمق 2.5 م"}},{"type":"Feature","id":21,"geometry":{"type":"Point","coordinates":[30.540886142000033,25.44329072000005]},"properties":{"OBJECTID":21,"Name":"مطبق","code":"502","description":"عمق 2.5 م"}},{"type":"Feature","id":22,"geometry":{"type":"Point","coordinates":[30.541427167000052,25.443257294000034]},"properties":{"OBJECTID":22,"Name":"مطبق","code":"502","description":"عمق 2.5 م"}},{"type":"Feature","id":29,"geometry":{"type":"Point","coordinates":[30.542041049000034,25.443225215000041]},"properties":{"OBJECTID":29,"Name":"مطبق","code":"502","description":"عمق 2.5 م"}},{"type":"Feature","id":30,"geometry":{"type":"Point","coordinates":[30.542526684000052,25.443197880000071]},"properties":{"OBJECTID":30,"Name":"مطبق","code":"502","description":"عمق 2.5 م"}},{"type":"Feature","id":34,"geometry":{"type":"Point","coordinates":[30.542816587000061,25.443118050000066]},"properties":{"OBJECTID":34,"Name":"مطبق","code":"502","description":"عمق 2.5 م"}},{"type":"Feature","id":35,"geometry":{"type":"Point","coordinates":[30.542627330000073,25.441316421000067]},"properties":{"OBJECTID":35,"Name":"مطبق","code":"501","description":"عمق 1.5 م"}},{"type":"Feature","id":36,"geometry":{"type":"Point","coordinates":[30.542486989000054,25.441323382000064]},"properties":{"OBJECTID":36,"Name":"مطبق","code":"501","description":"عمق 1.5 م"}},{"type":"Feature","id":37,"geometry":{"type":"Point","coordinates":[30.542421107000052,25.441194027000051]},"properties":{"OBJECTID":37,"Name":"مطبق","code":"501","description":"عمق 1.5 م"}},{"type":"Feature","id":38,"geometry":{"type":"Point","coordinates":[30.542608204000032,25.441190272000028]},"properties":{"OBJECTID":38,"Name":"مطبق","code":"501","description":"عمق 1.5 م"}}]
}